{
  "dayStartMin": 360,
  "dayEndMin": 1380,
  "rooms": [
    {
      "id": "1A",
      "label": "1A",
      "group": "south"
    },
    {
      "id": "1B",
      "label": "1B",
      "group": "south"
    },
    {
      "id": "2A",
      "label": "2A",
      "group": "south"
    },
    {
      "id": "2B",
      "label": "2B",
      "group": "south"
    },
    {
      "id": "3",
      "label": "3",
      "group": "fieldhouse"
    },
    {
      "id": "4",
      "label": "4",
      "group": "fieldhouse"
    },
    {
      "id": "5",
      "label": "5",
      "group": "fieldhouse"
    },
    {
      "id": "6",
      "label": "6",
      "group": "fieldhouse"
    },
    {
      "id": "7",
      "label": "7",
      "group": "fieldhouse"
    },
    {
      "id": "8",
      "label": "8",
      "group": "fieldhouse"
    },
    {
      "id": "9A",
      "label": "9A",
      "group": "north"
    },
    {
      "id": "9B",
      "label": "9B",
      "group": "north"
    },
    {
      "id": "10A",
      "label": "10A",
      "group": "north"
    },
    {
      "id": "10B",
      "label": "10B",
      "group": "north"
    }
  ],
  "slots": [
    {
      "roomId": "10A",
      "startMin": 1080,
      "endMin": 1260,
      "title": "D1 Training (Stay 22uned, Inc.), D1 Training (Stay 22uned, Inc.)",
      "subtitle": "Basketball",
      "orgKey": "d1 training (stay 22uned, inc.), d1 training (stay 22uned, inc.)",
      "rawRoomsCount": 1
    },
    {
      "roomId": "10B",
      "startMin": 1080,
      "endMin": 1260,
      "title": "D1 Training (Stay 22uned, Inc.), D1 Training (Stay 22uned, Inc.)",
      "subtitle": "Basketball",
      "orgKey": "d1 training (stay 22uned, inc.), d1 training (stay 22uned, inc.)",
      "rawRoomsCount": 1
    },
    {
      "roomId": "1A",
      "startMin": 1080,
      "endMin": 1170,
      "title": "WELCH VB",
      "subtitle": "Volleyball",
      "orgKey": "welch vb",
      "rawRoomsCount": 4
    },
    {
      "roomId": "1A",
      "startMin": 1080,
      "endMin": 1170,
      "title": "WELCH VB",
      "subtitle": "Volleyball",
      "orgKey": "welch vb",
      "rawRoomsCount": 4
    },
    {
      "roomId": "1A",
      "startMin": 1140,
      "endMin": 1260,
      "title": "Extreme Volleyball, Extreme Volleyball",
      "subtitle": "Volleyball",
      "orgKey": "extreme volleyball, extreme volleyball",
      "rawRoomsCount": 4
    },
    {
      "roomId": "1A",
      "startMin": 1260,
      "endMin": 1380,
      "title": "Chicago Sport and Social Club, Chicago Sport and Social Club",
      "subtitle": "Volleyball (Grab A Game)",
      "orgKey": "chicago sport and social club, chicago sport and social club",
      "rawRoomsCount": 1
    },
    {
      "roomId": "1B",
      "startMin": 1080,
      "endMin": 1170,
      "title": "WELCH VB",
      "subtitle": "Volleyball",
      "orgKey": "welch vb",
      "rawRoomsCount": 4
    },
    {
      "roomId": "1B",
      "startMin": 1080,
      "endMin": 1170,
      "title": "WELCH VB",
      "subtitle": "Volleyball",
      "orgKey": "welch vb",
      "rawRoomsCount": 4
    },
    {
      "roomId": "1B",
      "startMin": 1140,
      "endMin": 1260,
      "title": "Extreme Volleyball, Extreme Volleyball",
      "subtitle": "Volleyball",
      "orgKey": "extreme volleyball, extreme volleyball",
      "rawRoomsCount": 4
    },
    {
      "roomId": "1B",
      "startMin": 1260,
      "endMin": 1380,
      "title": "Chicago Sport and Social Club, Chicago Sport and Social Club",
      "subtitle": "Volleyball (Grab A Game)",
      "orgKey": "chicago sport and social club, chicago sport and social club",
      "rawRoomsCount": 1
    },
    {
      "roomId": "2A",
      "startMin": 1080,
      "endMin": 1170,
      "title": "WELCH VB",
      "subtitle": "Volleyball",
      "orgKey": "welch vb",
      "rawRoomsCount": 1
    },
    {
      "roomId": "2A",
      "startMin": 1140,
      "endMin": 1260,
      "title": "Extreme Volleyball, Extreme Volleyball",
      "subtitle": "Volleyball",
      "orgKey": "extreme volleyball, extreme volleyball",
      "rawRoomsCount": 2
    },
    {
      "roomId": "2A",
      "startMin": 1140,
      "endMin": 1260,
      "title": "Extreme Volleyball, Extreme Volleyball",
      "subtitle": "Volleyball",
      "orgKey": "extreme volleyball, extreme volleyball",
      "rawRoomsCount": 4
    },
    {
      "roomId": "2A",
      "startMin": 1260,
      "endMin": 1380,
      "title": "Chicago Sport and Social Club, Chicago Sport and Social Club",
      "subtitle": "Volleyball (Grab A Game)",
      "orgKey": "chicago sport and social club, chicago sport and social club",
      "rawRoomsCount": 1
    },
    {
      "roomId": "2B",
      "startMin": 1080,
      "endMin": 1170,
      "title": "WELCH VB",
      "subtitle": "Volleyball",
      "orgKey": "welch vb",
      "rawRoomsCount": 4
    },
    {
      "roomId": "2B",
      "startMin": 1080,
      "endMin": 1170,
      "title": "WELCH VB",
      "subtitle": "Volleyball",
      "orgKey": "welch vb",
      "rawRoomsCount": 2
    },
    {
      "roomId": "2B",
      "startMin": 1080,
      "endMin": 1170,
      "title": "WELCH VB",
      "subtitle": "Volleyball",
      "orgKey": "welch vb",
      "rawRoomsCount": 4
    },
    {
      "roomId": "2B",
      "startMin": 1140,
      "endMin": 1260,
      "title": "Extreme Volleyball, Extreme Volleyball",
      "subtitle": "Volleyball",
      "orgKey": "extreme volleyball, extreme volleyball",
      "rawRoomsCount": 1
    },
    {
      "roomId": "2B",
      "startMin": 1260,
      "endMin": 1380,
      "title": "Chicago Sport and Social Club, Chicago Sport and Social Club",
      "subtitle": "Volleyball (Grab A Game)",
      "orgKey": "chicago sport and social club, chicago sport and social club",
      "rawRoomsCount": 1
    },
    {
      "roomId": "3",
      "startMin": 540,
      "endMin": 1380,
      "title": "RAEC Front Desk, Rentals - On Hold",
      "subtitle": "Turf Season per NM",
      "orgKey": "raec front desk, rentals - on hold",
      "rawRoomsCount": 1
    },
    {
      "roomId": "4",
      "startMin": 540,
      "endMin": 1380,
      "title": "RAEC Front Desk, Rentals - On Hold",
      "subtitle": "Turf Season per NM",
      "orgKey": "raec front desk, rentals - on hold",
      "rawRoomsCount": 1
    },
    {
      "roomId": "5",
      "startMin": 540,
      "endMin": 1380,
      "title": "RAEC Front Desk, Rentals - On Hold",
      "subtitle": "Turf Season per NM",
      "orgKey": "raec front desk, rentals - on hold",
      "rawRoomsCount": 1
    },
    {
      "roomId": "6",
      "startMin": 540,
      "endMin": 1380,
      "title": "RAEC Front Desk, Rentals - On Hold",
      "subtitle": "Turf Season per NM",
      "orgKey": "raec front desk, rentals - on hold",
      "rawRoomsCount": 1
    },
    {
      "roomId": "7",
      "startMin": 540,
      "endMin": 1380,
      "title": "RAEC Front Desk, Rentals - On Hold",
      "subtitle": "Turf Season per NM",
      "orgKey": "raec front desk, rentals - on hold",
      "rawRoomsCount": 1
    },
    {
      "roomId": "8",
      "startMin": 540,
      "endMin": 1380,
      "title": "RAEC Front Desk, Rentals - On Hold",
      "subtitle": "Turf Season per NM",
      "orgKey": "raec front desk, rentals - on hold",
      "rawRoomsCount": 1
    },
    {
      "roomId": "9A",
      "startMin": 1080,
      "endMin": 1260,
      "title": "D1 Training (Stay 22uned, Inc.), D1 Training (Stay 22uned, Inc.)",
      "subtitle": "Basketball",
      "orgKey": "d1 training (stay 22uned, inc.), d1 training (stay 22uned, inc.)",
      "rawRoomsCount": 1
    },
    {
      "roomId": "9B",
      "startMin": 1080,
      "endMin": 1260,
      "title": "D1 Training (Stay 22uned, Inc.), D1 Training (Stay 22uned, Inc.)",
      "subtitle": "Basketball",
      "orgKey": "d1 training (stay 22uned, inc.), d1 training (stay 22uned, inc.)",
      "rawRoomsCount": 1
    }
  ]
}